pygeoprocessing/__init__.py
pygeoprocessing/extensions.pxd
pygeoprocessing/geoprocessing.py
pygeoprocessing/geoprocessing_core.cp310-win_amd64.pyd
pygeoprocessing/geoprocessing_core.cpp
pygeoprocessing/geoprocessing_core.pyx
pygeoprocessing/kernels.py
pygeoprocessing/slurm_utils.py
pygeoprocessing/symbolic.py
pygeoprocessing/utils.py
pygeoprocessing/extensions/FastFileIterator.h
pygeoprocessing/extensions/LRUCache.h
pygeoprocessing/extensions/ManagedRaster.h
pygeoprocessing/multiprocessing/__init__.py
pygeoprocessing/multiprocessing/raster_calculator.py
pygeoprocessing/routing/__init__.py
pygeoprocessing/routing/helper_functions.py
pygeoprocessing/routing/routing.cp310-win_amd64.pyd
pygeoprocessing/routing/routing.cpp
pygeoprocessing/routing/routing.pyx
pygeoprocessing/routing/watershed.cp310-win_amd64.pyd
pygeoprocessing/routing/watershed.cpp
pygeoprocessing/routing/watershed.pyx
pygeoprocessing-2.4.10.dist-info/licenses/LICENSE.txt
pygeoprocessing-2.4.10.dist-info/METADATA
pygeoprocessing-2.4.10.dist-info/WHEEL
pygeoprocessing-2.4.10.dist-info/top_level.txt
pygeoprocessing-2.4.10.dist-info/RECORD
