Metadata-Version: 2.4
Name: pygeoprocessing
Version: 2.4.10
Summary: PyGeoprocessing: Geoprocessing routines for GIS
Home-page: https://github.com/natcap/pygeoprocessing
Maintainer: Natural Capital Project Software Team
License: In this license, "Natural Capital Project" is defined as the parties of the
Keywords: gis,geoprocessing,pygeoprocessing
Classifier: Intended Audience :: Developers
Classifier: Development Status :: 5 - Production/Stable
Classifier: Intended Audience :: Science/Research
Classifier: Natural Language :: English
Classifier: Operating System :: MacOS :: MacOS X
Classifier: Operating System :: Microsoft
Classifier: Operating System :: POSIX
Classifier: Programming Language :: Python :: 3.9
Classifier: Programming Language :: Python :: 3.10
Classifier: Programming Language :: Python :: 3.11
Classifier: Programming Language :: Python :: 3.12
Classifier: Programming Language :: Python :: 3.13
Classifier: Programming Language :: Python :: Implementation :: CPython
Classifier: Topic :: Scientific/Engineering :: GIS
Classifier: License :: OSI Approved :: BSD License
Requires-Python: >=3.6
License-File: LICENSE.txt
Requires-Dist: GDAL>=3.0.4
Requires-Dist: numpy>=1.10.1
Requires-Dist: Rtree>=0.8.3
Requires-Dist: scipy!=0.19.1,>=0.14.1
Requires-Dist: Shapely>=1.6.4
Requires-Dist: importlib_metadata
Dynamic: description
Dynamic: description-content-type
Dynamic: home-page
Dynamic: license-file
Dynamic: requires-dist
